rpi_ad7606/__init__.py
rpi_ad7606/_version.py
rpi_ad7606/rpi_ad7606.py
rpi_ad7606-0.1.3.0.dist-info/DESCRIPTION.rst
rpi_ad7606-0.1.3.0.dist-info/METADATA
rpi_ad7606-0.1.3.0.dist-info/RECORD
rpi_ad7606-0.1.3.0.dist-info/WHEEL
rpi_ad7606-0.1.3.0.dist-info/metadata.json
rpi_ad7606-0.1.3.0.dist-info/top_level.txt
