Metadata-Version: 2.0
Name: rpi-ad7606
Version: 0.1.3.0
Summary: Alpha library for interfacing a Raspberry Pi with an Analog Devices AD7606 ADC.
Home-page: http://air.eece.wustl.edu/people/ben-sumlin/
Author: Benjamin Sumlin
Author-email: bsumlin@wustl.edu
License: MIT
Keywords: ADC
Platform: UNKNOWN
Classifier: Development Status :: 3 - Alpha
Classifier: Intended Audience :: Science/Research
Classifier: Programming Language :: Python :: 3 :: Only
Requires-Python: >=3
Requires-Dist: pigpio
